{"loc": "Bourbon", "iso": "US", "l1": "United States", "l2": "Kentucky", "lvl": 3, "pop": 19788, "isd": true, "ppd": 35.608, "med": 38.3, "p65": 15.413, "p70": 9.732, "hos": 2.77, "exp": 78.86, "adr": 0.0, "amn": 71559.0, "amv": 97802.0, "amd": 253.0, "amt": 811802.0, "key": 10445, "tmn": [859, 909, 1010, 909, 505, 909, 454, 404, 707, 960, 454, 1111, 404, 252, 505, 1465, 606, 656, 252, 50, 454], "tmv": [2887, 2642, 3430, 0, 0, 0, 0, 2481, 3099, 4739, 4340, 3978, 2687, 2448, 3374, 4677, 5132, 5139, 4690, 3336, 0], "tmd": [0, 0, 0, 0, 0, 0, 0, 0, 0, 0, 102, 0, 0, 0, 0, 0, 51, 0, 0, 0, 51], "wmn": 3993, "wmt": 20759, "wmd": 102, "wmv": 26350, "wdn": -7, "wdt": -1, "wdd": 0, "wdv": 11, "tlv": "Kentucky"}