{"loc": "Cherkasy Oblast", "iso": "UA", "l1": "Ukraine", "l2": "Cherkasy Oblast", "lvl": 2, "pop": 1206351, "isd": true, "ppd": 77.39, "med": 41.4, "p65": 16.462, "p70": 11.133, "hos": 8.8, "exp": 72.06, "adr": 1.0, "amn": 37826.0, "amv": 0.0, "amd": 453.0, "amt": 0.0, "key": 10741, "tmn": [250, 189, 253, 222, 254, 232, 267, 254, 99, 172, 165, 134, 161, 133, 64, 56, 101, 104, 85, 108, 128], "tmv": [0, 0, 0, 0, 0, 0, 0, 0, 0, 0, 0, 0, 0, 0, 0, 0, 0, 0, 0, 0, 0], "tmd": [0, 5, 4, 14, 10, 5, 4, 6, 3, 7, 10, 9, 5, 1, 0, 0, 4, 0, 12, 3, 8], "wmn": 650, "wmt": 0, "wmd": 25, "wmv": 0, "wdn": -42, "wdt": 0, "wdd": -35, "wdv": 0, "tlv": "Ukraine"}