{"loc": "Dhamtari", "iso": "IN", "l1": "India", "l2": "Chhattisgarh", "lvl": 3, "pop": 799199, "isd": true, "ppd": 450.419, "med": 28.2, "p65": 5.989, "p70": 3.414, "hos": 0.53, "exp": 69.66, "adr": 1.0, "amn": 10694.0, "amv": 2724.0, "amd": 159.0, "amt": 144094.0, "key": 11128, "tmn": [26, 17, 28, 47, 20, 11, 13, 8, 41, 22, 20, 22, 6, 23, 6, 21, -460, 18, 17, 8, 27], "tmv": [0, 0, 0, 0, 138, 23, 166, 159, 95, 171, 251, 138, 24, 295, 4, 236, 414, 414, 177, 10, 0], "tmd": [3, 3, 0, 0, 2, 0, 0, 2, 2, 0, 2, 0, 0, 3, 2, 0, 0, 2, 0, 0, 0], "wmn": -360, "wmt": 4419, "wmd": 3, "wmv": 1258, "wdn": -348, "wdt": -13, "wdd": -60, "wdv": 11, "tlv": "Chhattisgarh"}