{"loc": "Abbeville", "iso": "US", "l1": "United States", "l2": "South Carolina", "lvl": 3, "pop": 24527, "key": 10001, "isd": true, "ppd": 35.608000000000004, "med": 38.3, "p65": 15.413, "p70": 9.732000000000001, "hos": 2.77, "exp": 78.86, "adr": 1.0, "amn": 161414.0, "amv": 1393875.0, "amd": 2039.0, "amt": 1956475.0, "tmn": [163, 0, 163, 0, 0, 407, 0, 81, 203, 244, 0, 0, 652, 163, 122, -40, 448, 0, 0, 774, 40], "tmv": [4933, 4463, 5576, 3317, 1660, 4353, 4663, 4819, 4832, 5563, 3334, 1728, 4724, 4234, 2965, 50, 2434, 1138, 149, 0, 0], "tmd": [0, 0, 0, 0, 0, 0, 0, 0, 0, 0, 0, 0, 0, 0, 0, 0, 0, 0, 0, 0, 0], "wmn": 1346, "wmt": 17307, "wmd": 0, "wmv": 6738, "wdn": 0, "wdt": -34, "wdd": 0, "wdv": -77, "tlv": "South Carolina"}