{"loc": "Albania", "iso": "AL", "l1": "Albania", "l2": "0", "lvl": 1, "pop": 2877800, "key": 10052, "isd": true, "ppd": 104.87100000000001, "med": 38.0, "p65": 13.187999999999999, "p70": 8.642999999999999, "hos": 2.89, "exp": 78.57, "adr": 2.0, "amn": 46074.0, "amv": 355411.0, "amd": 853.0, "amt": 0.0, "tmn": [0, 2, 0, 0, 2, 1, 1, 0, 0, 2, 0, 1, 2, 0, 0, 2, 4, 2, 5, 2, 1], "tmv": [3176, 3953, 3976, 3479, 0, 0, 0, 0, 4190, 4356, 2241, 2436, 0, 0, 1921, 2078, 1945, 1957, 1826, 1686, 484], "tmd": [0, 1, 0, 0, 0, 1, 0, 0, 0, 0, 0, 0, 0, 0, 0, 0, 0, 0, 0, 0, 0], "wmn": 20, "wmt": 0, "wmd": 0, "wmv": 11903, "wdn": 148, "wdt": 0, "wdd": 0, "wdv": -10, "tlv": "Albania"}