{"loc": "Anantnag", "iso": "IN", "l1": "India", "l2": "Jammu and Kashmir", "lvl": 3, "pop": 1070144, "key": 10108, "isd": true, "ppd": 450.41900000000004, "med": 28.2, "p65": 5.989, "p70": 3.4139999999999997, "hos": 0.53, "exp": 69.66, "adr": 2.0, "amn": 4635.0, "amv": 6319.0, "amd": 80.0, "amt": 357815.0, "tmn": [1, 5, 4, 3, 3, 2, 1, 1, 5, 4, 5, 4, 6, 3, 0, 1, 4, 0, 2, 6, 0], "tmv": [4, 236, 414, 414, 177, 10, 138, 136, 225, 369, 331, 259, 26, 323, 255, 293, 353, 335, 214, 15, 315], "tmd": [0, 0, 0, 1, 0, 0, 0, 0, 1, 0, 0, 0, 0, 0, 0, 0, 0, 0, 0, 0, 0], "wmn": 19, "wmt": 11606, "wmd": 0, "wmv": 1784, "wdn": -43, "wdt": 6, "wdd": -100, "wdv": 7, "tlv": "Jammu and Kashmir"}