{"loc": "Antofagasta", "iso": "CL", "l1": "Chile", "l2": "Antofagasta", "lvl": 2, "pop": 607534, "key": 10136, "isd": true, "ppd": 24.281999999999996, "med": 35.4, "p65": 11.087, "p70": 6.938, "hos": 2.11, "exp": 80.18, "adr": 2.0, "amn": 99206.0, "amv": 1398165.0, "amd": 2013.0, "amt": 1008980.0, "tmn": [72, 54, 49, 41, 51, 13, 85, 90, 200, 67, 31, 29, 9, 100, 118, 88, 18, 26, 26, 8, 8], "tmv": [4721, 4013, 585, 24, 6490, 7268, 3381, 2419, 1812, 60, 3, 5135, 4581, 6297, 4248, 2663, 67, 21, 0, 0, 0], "tmd": [9, 4, 2, 5, 4, 0, 0, 4, 10, 2, 4, 14, 0, 0, 5, 0, 2, 0, 2, 0, 0], "wmn": 295, "wmt": 15947, "wmd": 9, "wmv": 7001, "wdn": -44, "wdt": -18, "wdd": -74, "wdv": -66, "tlv": "Chile"}