{"loc": "Aransas", "iso": "US", "l1": "United States", "l2": "Texas", "lvl": 3, "pop": 23510, "key": 10147, "isd": true, "ppd": 35.608000000000004, "med": 38.3, "p65": 15.413, "p70": 9.732000000000001, "hos": 2.77, "exp": 78.86, "adr": 3.0, "amn": 69077.0, "amv": 0.0, "amd": 1957.0, "amt": 957873.0, "tmn": [425, 255, 212, 425, 0, 552, 170, 42, 510, 85, 510, 0, 595, 382, 1105, 935, 850, 893, 0, 935, 1531], "tmv": [0, 0, 0, 0, 0, 0, 0, 0, 0, 0, 0, 0, 0, 0, 0, 0, 0, 0, 0, 0, 0], "tmd": [43, 43, 0, 0, 0, 0, 0, 0, 0, 0, 0, 0, 0, 0, 86, 43, 0, 0, 0, 0, 0], "wmn": 6253, "wmt": 15831, "wmd": 128, "wmv": 0, "wdn": 194, "wdt": -17, "wdd": 0, "wdv": 0, "tlv": "Texas"}