{"loc": "Asturias", "iso": "ES", "l1": "Spain", "l2": "Asturias", "lvl": 2, "pop": 1022205, "key": 10186, "isd": true, "ppd": 93.105, "med": 45.5, "p65": 19.436, "p70": 13.799000000000001, "hos": 2.97, "exp": 83.56, "adr": 3.0, "amn": 78438.0, "amv": 1734688.0, "amd": 2071.0, "amt": 1422506.0, "tmn": [203, 219, 0, 0, 606, 218, 287, 308, 321, 0, 0, 0, 1389, 0, 735, 388, 0, 0, 1483, 502, 646], "tmv": [9696, 0, 0, 0, 7742, 4161, 4692, 5513, 0, 0, 0, 0, 0, 0, 3726, 0, 0, 0, 9790, 0, 0], "tmd": [0, 1, 0, 0, 3, 0, 3, 0, 0, 0, 0, 0, 0, 0, 11, 3, 0, 0, 4, 1, 4], "wmn": 3757, "wmt": 0, "wmd": 23, "wmv": 13517, "wdn": 86, "wdt": 0, "wdd": 0, "wdv": 145, "tlv": "Spain"}