{"loc": "Atlantico", "iso": "CO", "l1": "Colombia", "l2": "Atlantico", "lvl": 2, "pop": 2535517, "key": 10194, "isd": true, "ppd": 44.223, "med": 32.2, "p65": 7.646, "p70": 4.312, "hos": 1.71, "exp": 77.29, "adr": 3.0, "amn": 121560.0, "amv": 540936.0, "amd": 3634.0, "amt": 438636.0, "tmn": [1, 454, 215, 175, 242, 261, 0, 0, 0, 798, 168, 0, 317, 202, 120, 150, 195, 156, 151, 213, 117], "tmv": [5300, 0, 0, 6252, 0, 0, 2863, 3942, 3300, 0, 0, 5711, 0, 0, 5663, 0, 0, 6458, 0, 0, 0], "tmd": [6, 3, 6, 2, 4, 4, 3, 1, 4, 3, 1, 0, 3, 4, 2, 2, 5, 2, 3, 4, 2], "wmn": 1106, "wmt": 5370, "wmd": 18, "wmv": 12122, "wdn": -26, "wdt": -44, "wdd": 36, "wdv": -6, "tlv": "Colombia"}