{"loc": "Baja California", "iso": "MX", "l1": "Mexico", "l2": "Baja California", "lvl": 2, "pop": 3634868, "key": 10231, "isd": true, "ppd": 66.444, "med": 29.3, "p65": 6.857, "p70": 4.321000000000001, "hos": 1.38, "exp": 75.05, "adr": 17.0, "amn": 12789.0, "amv": 67645.0, "amd": 2146.0, "amt": 44372.0, "tmn": [8, 5, 0, 2, 15, 8, 14, 10, 2, 2, 19, 17, 16, 15, 17, 3, 2, 3, 12, 13, 9], "tmv": [1636, 983, 506, 987, 1618, 1642, 1872, 2130, 1199, 1322, 1139, 1505, 974, 1903, 1859, 1000, 1297, 3024, 3491, 0, 0], "tmd": [4, 1, 1, 1, 1, 5, 4, 5, 1, 1, 4, 2, 2, 2, 3, 1, 0, 2, 6, 3, 1], "wmn": 63, "wmt": 426, "wmd": 14, "wmv": 10673, "wdn": -26, "wdt": -52, "wdd": -9, "wdv": 5, "tlv": "Mexico"}