{"loc": "Bangladesh", "iso": "BD", "l1": "Bangladesh", "l2": "0", "lvl": 1, "pop": 164689383, "key": 10257, "isd": true, "ppd": 1265.036, "med": 27.5, "p65": 5.098, "p70": 3.262, "hos": 0.8, "exp": 72.59, "adr": 2.0, "amn": 9592.0, "amv": 781898.0, "amd": 170.0, "amt": 67526.0, "tmn": [1, 1, 1, 1, 0, 1, 1, 1, 1, 1, 1, 0, 2, 1, 1, 1, 1, 1, 1, 1, 2], "tmv": [0, 0, 6024, 0, 0, 0, 11663, 4415, 12941, 7928, 0, 0, 5526, 5970, 3502, 8924, 8723, 125134, 3990, 5644, 0], "tmd": [1, 1, 1, 1, 1, 1, 1, 1, 1, 1, 1, 0, 1, 1, 1, 1, 0, 1, 1, 1, 1], "wmn": 13, "wmt": 859, "wmd": 1, "wmv": 155921, "wdn": 16, "wdt": 7, "wdd": 4, "wdv": 324, "tlv": "Bangladesh"}