{"loc": "Biobio", "iso": "CL", "l1": "Chile", "l2": "Biobio", "lvl": 2, "pop": 1556805, "key": 10396, "isd": true, "ppd": 24.281999999999996, "med": 35.4, "p65": 11.087, "p70": 6.938, "hos": 2.11, "exp": 80.18, "adr": 2.0, "amn": 97418.0, "amv": 1701327.0, "amd": 1726.0, "amt": 1141436.0, "tmn": [29, 32, 27, 27, 29, 24, 14, 25, 37, 32, 41, 26, 28, 25, 21, 34, 18, 28, 27, 16, 19], "tmv": [7355, 3482, 9, 0, 0, 7614, 8293, 8711, 7516, 7781, 142, 16, 10380, 12154, 11523, 10374, 6092, 0, 0, 0, 0], "tmd": [0, 1, 2, 1, 3, 0, 0, 0, 4, 3, 1, 1, 1, 0, 0, 2, 2, 1, 1, 0, 0], "wmn": 168, "wmt": 19121, "wmd": 4, "wmv": 27991, "wdn": -23, "wdt": -13, "wdd": -54, "wdv": -40, "tlv": "Chile"}