{"loc": "Bolivia", "iso": "BO", "l1": "Bolivia", "l2": "0", "lvl": 1, "pop": 11673029, "key": 10418, "isd": true, "ppd": 10.202, "med": 25.4, "p65": 6.704, "p70": 4.393, "hos": 1.1, "exp": 71.51, "adr": 4.0, "amn": 36767.0, "amv": 191196.0, "amd": 1406.0, "amt": 144331.0, "tmn": [257, 195, 122, 0, 497, 0, 605, 0, 454, 137, 184, 220, 242, 229, 0, 322, 93, 65, 142, 194, 208], "tmv": [3273, 921, 335, 4209, 0, 0, 0, 0, 0, 380, 0, 0, 0, 0, 2601, 0, 0, 0, 0, 0, 0], "tmd": [6, 7, 4, 0, 14, 0, 13, 0, 15, 5, 7, 11, 8, 9, 0, 15, 4, 4, 6, 8, 8], "wmn": 1027, "wmt": 0, "wmd": 42, "wmv": 2602, "wdn": -30, "wdt": -100, "wdd": -19, "wdv": 584, "tlv": "Bolivia"}