{"loc": "Castilla - La Mancha", "iso": "ES", "l1": "Spain", "l2": "Castilla - La Mancha", "lvl": 2, "pop": 2034877, "key": 10666, "isd": true, "ppd": 93.105, "med": 45.5, "p65": 19.436, "p70": 13.799000000000001, "hos": 2.97, "exp": 83.56, "adr": 3.0, "amn": 114936.0, "amv": 1441254.0, "amd": 3098.0, "amt": 1186578.0, "tmn": [336, 349, 0, 0, 491, 305, 326, 312, 325, 0, 0, 553, 232, 179, 246, 189, 0, 0, 373, 153, 113], "tmv": [9099, 0, 0, 0, 7430, 8011, 8588, 6876, 0, 0, 0, 4879, 9778, 7154, 6920, 0, 0, 0, 4166, 0, 0], "tmd": [1, 7, 0, 0, 16, 2, 30, 6, 6, 0, 0, 13, 4, 2, 5, 19, 0, 0, 8, 4, 1], "wmn": 1078, "wmt": 0, "wmd": 36, "wmv": 11088, "wdn": -33, "wdt": 0, "wdd": 18, "wdv": -61, "tlv": "Spain"}