{"loc": "Chelyabinsk Oblast", "iso": "RU", "l1": "Russia", "l2": "Chelyabinsk Oblast", "lvl": 2, "pop": 3493036, "key": 10736, "isd": true, "ppd": 8.823, "med": 39.6, "p65": 14.177999999999999, "p70": 9.392999999999999, "hos": 8.05, "exp": 72.58, "adr": 2.0, "amn": 17180.0, "amv": 149686.0, "amd": 429.0, "amt": 903997.0, "tmn": [32, 32, 31, 32, 31, 31, 30, 30, 30, 29, 30, 30, 30, 30, 29, 29, 29, 28, 28, 28, 28], "tmv": [1736, 2720, 2175, 3732, 494, 1114, 1656, 3335, 3289, 2127, 685, 934, 272, 396, 3780, 3135, 815, 2057, 0, 0, 399], "tmd": [3, 3, 3, 2, 2, 2, 3, 3, 3, 2, 2, 2, 2, 2, 3, 2, 3, 2, 3, 3, 3], "wmn": 202, "wmt": 10356, "wmd": 15, "wmv": 10189, "wdn": -4, "wdt": 24, "wdd": 20, "wdv": -8, "tlv": "Russia"}