{"loc": "Chiapas", "iso": "MX", "l1": "Mexico", "l2": "Chiapas", "lvl": 2, "pop": 5730367, "key": 10767, "isd": true, "ppd": 66.444, "med": 29.3, "p65": 6.857, "p70": 4.321000000000001, "hos": 1.38, "exp": 75.05, "adr": 14.0, "amn": 1744.0, "amv": 19212.0, "amd": 250.0, "amt": 38714.0, "tmn": [4, 2, 4, 3, 3, 3, 0, 5, 2, 7, 1, 5, 5, 1, 0, 3, 3, 4, 3, 2, 0], "tmv": [33, 51, 2, 5, 4, 2, 0, 0, 1296, 1117, 2033, 2004, 642, 257, 346, 530, 779, 1471, 1425, 879, 560], "tmd": [1, 2, 1, 1, 1, 1, 1, 1, 1, 1, 1, 1, 1, 1, 1, 1, 1, 1, 1, 1, 1], "wmn": 18, "wmt": 458, "wmd": 3, "wmv": 5994, "wdn": -40, "wdt": -58, "wdd": 0, "wdv": -18, "tlv": "Mexico"}