{"loc": "Choco", "iso": "CO", "l1": "Colombia", "l2": "Choco", "lvl": 2, "pop": 534826, "key": 10788, "isd": true, "ppd": 44.223, "med": 32.2, "p65": 7.646, "p70": 4.312, "hos": 1.71, "exp": 77.29, "adr": 2.0, "amn": 30937.0, "amv": 1186764.0, "amd": 754.0, "amt": 561430.0, "tmn": [13, 5, 13, 0, 3, 1, 1, 5, 0, 18, 0, 3, 9, 0, 0, 16, 5, 5, 5, 11, 5], "tmv": [7941, 8041, 0, 0, 6275, 3666, 7524, 8515, 14360, 0, 0, 0, 0, 6004, 5197, 0, 0, 6786, 0, 0, 0], "tmd": [0, 0, 0, 0, 0, 0, 0, 2, 0, 0, 0, 0, 2, 2, 0, 0, 0, 0, 0, 0, 0], "wmn": 51, "wmt": 4769, "wmd": 0, "wmv": 11984, "wdn": 35, "wdt": -24, "wdd": -100, "wdv": -59, "tlv": "Colombia"}