{"loc": "Ciudad de Mexico", "iso": "MX", "l1": "Mexico", "l2": "Ciudad de Mexico", "lvl": 2, "pop": 9018645, "key": 10807, "isd": true, "ppd": 66.444, "med": 29.3, "p65": 6.857, "p70": 4.321000000000001, "hos": 1.38, "exp": 75.05, "adr": 5.0, "amn": 72291.0, "amv": 189552.0, "amd": 3664.0, "amt": 50216.0, "tmn": [124, 116, 94, 48, 30, 88, 88, 92, 90, 74, 29, 13, 73, 86, 106, 79, 79, 32, 14, 76, 49], "tmv": [2823, 2826, 1930, 1134, 2785, 4011, 4780, 4614, 3660, 1719, 563, 0, 0, 3108, 3340, 0, 0, 0, 1044, 7210, 0], "tmd": [7, 8, 3, 2, 2, 4, 5, 5, 6, 4, 1, 2, 3, 4, 2, 4, 5, 2, 1, 4, 2], "wmn": 439, "wmt": 174, "wmd": 18, "wmv": 11595, "wdn": -5, "wdt": -72, "wdd": -22, "wdv": -15, "tlv": "Mexico"}