{"loc": "Coahuila", "iso": "MX", "l1": "Mexico", "l2": "Coahuila", "lvl": 2, "pop": 3218720, "key": 10876, "isd": true, "ppd": 66.444, "med": 29.3, "p65": 6.857, "p70": 4.321000000000001, "hos": 1.38, "exp": 75.05, "adr": 8.0, "amn": 29251.0, "amv": 992898.0, "amd": 2307.0, "amt": 85052.0, "tmn": [18, 6, 65, 57, 49, 45, 45, 0, 19, 0, 66, 110, 52, 42, 10, 0, 2, 57, 37, 53, 101], "tmv": [0, 12707, 3167, 3073, 3718, 3806, 4700, 4911, 3432, 12647, 0, 0, 0, 56702, 1905, 703, 0, 0, 2837, 0, 0], "tmd": [0, 2, 4, 4, 1, 5, 1, 0, 2, 0, 5, 4, 5, 3, 1, 0, 1, 4, 2, 3, 1], "wmn": 263, "wmt": 286, "wmd": 9, "wmv": 5446, "wdn": -10, "wdt": -66, "wdd": -42, "wdv": -93, "tlv": "Mexico"}