{"loc": "Cundinamarca", "iso": "CO", "l1": "Colombia", "l2": "Cundinamarca", "lvl": 2, "pop": 2919060, "key": 11008, "isd": true, "ppd": 44.223, "med": 32.2, "p65": 7.646, "p70": 4.312, "hos": 1.71, "exp": 77.29, "adr": 3.0, "amn": 51565.0, "amv": 157399.0, "amd": 1412.0, "amt": 316485.0, "tmn": [382, 274, 305, 229, 230, 229, 314, 316, 390, 424, 461, 358, 401, 349, 305, 392, 401, 483, 415, 285, 698], "tmv": [2115, 0, 0, 0, 0, 0, 0, 0, 0, 3827, 3490, 3802, 0, 0, 1668, 1541, 3547, 2840, 2871, 0, 0], "tmd": [6, 17, 8, 11, 7, 7, 6, 7, 8, 11, 15, 16, 16, 13, 14, 20, 12, 10, 18, 10, 25], "wmn": 2982, "wmt": 5549, "wmd": 106, "wmv": 12470, "wdn": 10, "wdt": -43, "wdd": 28, "wdv": 12, "tlv": "Colombia"}