{"loc": "Delhi", "iso": "IN", "l1": "India", "l2": "Delhi", "lvl": 2, "pop": 18710922, "key": 11104, "isd": true, "ppd": 450.41900000000004, "med": 28.2, "p65": 5.989, "p70": 3.4139999999999997, "hos": 0.53, "exp": 69.66, "adr": 2.0, "amn": 76778.0, "amv": 358932.0, "amd": 1339.0, "amt": 342856.0, "tmn": [3, 3, 2, 1, 2, 3, 2, 0, 6, 3, 2, 4, 3, 2, 3, 3, 4, 2, 2, 3, 3], "tmv": [3153, 3794, 0, 0, 2627, 1723, 4033, 3235, 3817, 1481, 4866, 3075, 3296, 3860, 3974, 0, 0, 0, 0, 2938, 4337], "tmd": [1, 1, 0, 1, 1, 1, 1, 0, 1, 1, 1, 1, 1, 0, 1, 1, 1, 0, 1, 0, 1], "wmn": 24, "wmt": 7618, "wmd": 1, "wmv": 11251, "wdn": 3, "wdt": -10, "wdd": 22, "wdv": -52, "tlv": "India"}