{"loc": "Donetsk Oblast", "iso": "UA", "l1": "Ukraine", "l2": "Donetsk Oblast", "lvl": 2, "pop": 4165901, "isd": true, "ppd": 77.39, "med": 41.4, "p65": 16.462, "p70": 11.133, "hos": 8.8, "exp": 72.06, "adr": 2.0, "amn": 10712.0, "amv": 0.0, "amd": 236.0, "amt": 145207.0, "key": 11172, "tmn": [129, 56, 21, 41, 49, 67, 63, 46, 26, 30, 11, 34, 48, 46, 40, 42, 14, 13, 24, 38, 35], "tmv": [0, 0, 0, 0, 0, 0, 0, 0, 0, 0, 0, 0, 0, 0, 0, 0, 0, 0, 0, 0, 0], "tmd": [3, 2, 0, 2, 3, 4, 0, 3, 0, 0, 3, 4, 5, 7, 7, 0, 0, 7, 7, 6, 3], "wmn": 209, "wmt": 578, "wmd": 27, "wmv": 0, "wdn": -14, "wdt": -75, "wdd": 42, "wdv": 0, "tlv": "Ukraine"}