{"loc": "Durango", "iso": "MX", "l1": "Mexico", "l2": "Durango", "lvl": 2, "pop": 1868996, "key": 11206, "isd": true, "ppd": 66.444, "med": 29.3, "p65": 6.857, "p70": 4.321000000000001, "hos": 1.38, "exp": 75.05, "adr": 7.0, "amn": 16133.0, "amv": 5866.0, "amd": 1068.0, "amt": 36498.0, "tmn": [72, 37, 90, 113, 87, 19, 3, 8, 29, 0, 183, 71, 21, 5, 46, 73, 81, 93, 51, 12, 3], "tmv": [56, 29, 14, 34, 63, 23, 14, 18, 70, 66, 40, 77, 25, 33, 51, 2, 5, 4, 2, 0, 0], "tmd": [11, 4, 7, 10, 8, 0, 0, 0, 16, 0, 10, 7, 0, 0, 7, 7, 8, 7, 3, 5, 0], "wmn": 363, "wmt": 742, "wmd": 35, "wmv": 67, "wdn": 13, "wdt": -47, "wdd": 10, "wdv": -80, "tlv": "Mexico"}