{"loc": "East Flanders", "iso": "BE", "l1": "Belgium", "l2": "East Flanders", "lvl": 2, "pop": 1515064, "key": 11219, "isd": true, "ppd": 375.564, "med": 41.8, "p65": 18.570999999999998, "p70": 12.849, "hos": 5.64, "exp": 81.63, "adr": 0.0, "amn": 92659.0, "amv": 1431135.0, "amd": 0.0, "amt": 1716220.0, "tmn": [116, 100, 0, 0, 284, 73, 146, 112, 111, 0, 0, 285, 105, 144, 108, 106, 0, 0, 200, 73, 130], "tmv": [940, 1553, 1935, 112, 690, 391, 1411, 1038, 1415, 1771, 32, 507, 864, 1425, 884, 1162, 1949, 60, 476, 596, 0], "tmd": [0, 0, 0, 0, 0, 0, 0, 0, 0, 0, 0, 0, 0, 0, 0, 0, 0, 0, 0, 0, 0], "wmn": 620, "wmt": 14592, "wmd": 0, "wmv": 5130, "wdn": -18, "wdt": -50, "wdd": 0, "wdv": -27, "tlv": "Belgium"}