{"loc": "Ecuador", "iso": "EC", "l1": "Ecuador", "l2": "0", "lvl": 1, "pop": 17643060, "key": 11232, "isd": true, "ppd": 66.939, "med": 28.1, "p65": 7.104, "p70": 4.458, "hos": 1.5, "exp": 77.01, "adr": 5.0, "amn": 19868.0, "amv": 25929.0, "amd": 986.0, "amt": 64549.0, "tmn": [104, 158, 70, 101, 36, 124, 81, 92, 93, 64, 142, 62, 52, 107, 114, 60, 124, 109, 14, 29, 167], "tmv": [0, 0, 239, 0, 0, 0, 0, 0, 0, 0, 0, 1928, 1229, 0, 0, 0, 0, 0, 0, 0, 0], "tmd": [3, 3, 3, 4, 1, 2, 4, 2, 2, 2, 2, 2, 1, 4, 4, 3, 7, 2, 1, 4, 3], "wmn": 620, "wmt": 1118, "wmd": 20, "wmv": 0, "wdn": 1, "wdt": -34, "wdd": 63, "wdv": -100, "tlv": "Ecuador"}