{"loc": "Ecuador", "iso": "EC", "l1": "Ecuador", "l2": "0", "lvl": 1, "pop": 17643060, "key": 11232, "isd": true, "ppd": 66.939, "med": 28.1, "p65": 7.104, "p70": 4.458, "hos": 1.5, "exp": 77.01, "adr": 5.0, "amn": 25752.0, "amv": 223558.0, "amd": 1220.0, "amt": 82640.0, "tmn": [21, 13, 50, 122, 62, 55, 46, 11, 13, 102, 65, 116, 67, 48, 10, 30, 109, 21, 155, 64, 55], "tmv": [2905, 4034, 0, 0, 0, 0, 0, 0, 0, 0, 0, 0, 0, 1270, 4396, 3806, 4096, 4642, 3666, 0, 0], "tmd": [1, 1, 5, 3, 3, 2, 2, 1, 1, 6, 2, 4, 3, 1, 1, 1, 3, 1, 4, 3, 3], "wmn": 448, "wmt": 676, "wmd": 14, "wmv": 20609, "wdn": 5, "wdt": -58, "wdd": -6, "wdv": 1522, "tlv": "Ecuador"}