{"loc": "Extremadura", "iso": "ES", "l1": "Spain", "l2": "Extremadura", "lvl": 2, "pop": 1065424, "key": 11299, "isd": true, "ppd": 93.105, "med": 45.5, "p65": 19.436, "p70": 13.799, "hos": 2.97, "exp": 83.56, "adr": 2.0, "amn": 63733.0, "amv": 47765.0, "amd": 1520.0, "amt": 640417.0, "tmn": [993, 0, 0, 2162, 682, 746, 703, 702, 0, 0, 1127, 365, 366, 320, 271, 0, 0, 475, 234, 143, 132], "tmv": [1337, 0, 0, 1146, 1395, 837, 1680, 0, 0, 0, 1364, 1961, 2150, 2626, 0, 0, 0, 1330, 1411, 0, 0], "tmd": [19, 0, 0, 43, 23, 28, 25, 14, 0, 0, 40, 21, 20, 15, 24, 0, 0, 37, 11, 11, 4], "wmn": 1258, "wmt": 0, "wmd": 85, "wmv": 2743, "wdn": -56, "wdt": 0, "wdd": -21, "wdv": -66, "tlv": "Spain"}