{"loc": "Ethiopia", "iso": "ET", "l1": "Ethiopia", "l2": "0", "lvl": 1, "pop": 114963583, "key": 11293, "isd": true, "ppd": 104.95700000000001, "med": 19.8, "p65": 3.5260000000000002, "p70": 2.063, "hos": 0.3, "exp": 66.6, "adr": 2.0, "amn": 2408.0, "amv": 17876.0, "amd": 38.0, "amt": 25262.0, "tmn": [1, 1, 1, 0, 0, 0, 1, 0, 0, 0, 0, 1, 0, 0, 0, 0, 0, 0, 0, 1, 0], "tmv": [10, 2, 0, 0, 43, 5, 3, 4, 3, 121, 59, 78, 25, 66, 43, 17, 95, 15, 32, 15, 0], "tmd": [1, 1, 1, 1, 1, 1, 1, 1, 1, 1, 1, 0, 1, 1, 1, 1, 1, 1, 1, 1, 1], "wmn": 5, "wmt": 166, "wmd": 1, "wmv": 221, "wdn": -1, "wdt": -39, "wdd": -40, "wdv": -39, "tlv": "Ethiopia"}