{"loc": "Fukushima", "iso": "JP", "l1": "Japan", "l2": "Fukushima", "lvl": 2, "pop": 1845519, "key": 11425, "isd": true, "ppd": 347.778, "med": 48.2, "p65": 27.049, "p70": 18.493, "hos": 13.05, "exp": 84.63, "adr": 4.0, "amn": 1644.0, "amv": 17319.0, "amd": 63.0, "amt": 82094.0, "tmn": [11, 18, 0, 15, 22, 15, 6, 17, 40, 0, 17, 1, 4, 7, 26, 0, 25, 11, 20, 0, 26], "tmv": [419, 374, 368, 0, 0, 0, 724, 826, 747, 829, 0, 0, 0, 439, 417, 432, 0, 0, 0, 986, 1071], "tmd": [0, 1, 1, 1, 1, 0, 0, 0, 0, 0, 1, 0, 0, 0, 0, 0, 0, 0, 0, 0, 1], "wmn": 110, "wmt": 3172, "wmd": 1, "wmv": 2909, "wdn": 24, "wdt": 1, "wdd": 0, "wdv": 2, "tlv": "Japan"}