{"loc": "Ghana", "iso": "GH", "l1": "Ghana", "l2": "0", "lvl": 1, "pop": 31072945, "key": 11488, "isd": true, "ppd": 126.719, "med": 21.1, "p65": 3.385, "p70": 1.9480000000000002, "hos": 0.9, "exp": 64.07, "adr": 1.0, "amn": 3951.0, "amv": 0.0, "amd": 35.0, "amt": 0.0, "tmn": [33, 20, 16, 13, 0, 29, 19, 19, 0, 20, 37, 0, 18, 14, 0, 0, 27, 27, 12, 0, 7], "tmv": [0, 0, 0, 0, 0, 0, 0, 0, 0, 0, 0, 0, 0, 0, 0, 0, 0, 0, 0, 0, 0], "tmd": [1, 1, 1, 1, 0, 1, 1, 1, 0, 1, 1, 0, 1, 1, 0, 0, 1, 1, 1, 0, 1], "wmn": 75, "wmt": 0, "wmd": 2, "wmv": 0, "wdn": -32, "wdt": 0, "wdd": -31, "wdv": 0, "tlv": "Ghana"}