{"loc": "Gotland", "iso": "SE", "l1": "Sweden", "l2": "Gotland", "lvl": 2, "pop": 59686, "key": 11535, "isd": true, "ppd": 24.718000000000004, "med": 41.0, "p65": 19.985, "p70": 13.433, "hos": 2.22, "exp": 82.8, "adr": 1.0, "amn": 64035.0, "amv": 413662.0, "amd": 854.0, "amt": 0.0, "tmn": [0, 0, 854, 234, 100, 217, 0, 0, 0, 770, 234, 469, 167, 0, 0, 0, 887, 251, 0, 653, 0], "tmv": [0, 0, 0, 0, 0, 0, 0, 0, 0, 0, 0, 0, 11470, 0, 0, 0, 0, 4713, 0, 0, 0], "tmd": [0, 0, 17, 0, 17, 17, 0, 0, 0, 0, 0, 0, 0, 0, 0, 0, 0, 0, 0, 0, 0], "wmn": 1793, "wmt": 5059, "wmd": 0, "wmv": 4714, "wdn": 9, "wdt": -86, "wdd": 0, "wdv": -59, "tlv": "Sweden"}