{"loc": "Guanajuato", "iso": "MX", "l1": "Mexico", "l2": "Guanajuato", "lvl": 2, "pop": 6228175, "key": 11620, "isd": true, "ppd": 66.444, "med": 29.3, "p65": 6.857, "p70": 4.321000000000001, "hos": 1.38, "exp": 75.05, "adr": 7.0, "amn": 28725.0, "amv": 824152.0, "amd": 1961.0, "amt": 80717.0, "tmn": [0, 137, 22, 146, 153, 151, 145, 0, 150, 27, 144, 139, 125, 128, 116, 0, 53, 0, 140, 258, 115], "tmv": [3234, 2873, 3458, 5575, 5716, 5938, 4795, 2278, 1407, 3930, 5073, 5270, 4631, 0, 0, 0, 0, 0, 0, 0, 0], "tmd": [0, 7, 2, 9, 5, 9, 3, 0, 6, 2, 2, 4, 6, 3, 4, 0, 2, 0, 4, 5, 4], "wmn": 685, "wmt": 490, "wmd": 19, "wmv": 0, "wdn": -4, "wdt": -54, "wdd": -10, "wdv": -100, "tlv": "Mexico"}