{"loc": "Hartford", "iso": "US", "l1": "United States", "l2": "Connecticut", "lvl": 3, "pop": 891720, "isd": true, "ppd": 35.608, "med": 38.3, "p65": 15.413, "p70": 9.732, "hos": 2.77, "exp": 78.86, "adr": 3.0, "amn": 73086.0, "amv": 102828.0, "amd": 2422.0, "amt": 1658302.0, "key": 11736, "tmn": [410, 0, 0, 2065, 640, 495, 477, 509, 0, 0, 1770, 334, 690, 440, 334, 0, 0, 1181, 620, 118, 278], "tmv": [3430, 0, 0, 0, 0, 2481, 3099, 4739, 4340, 3978, 2687, 2448, 3374, 4677, 5132, 5139, 4690, 3336, 1695, 3330, 0], "tmd": [13, 0, 0, 24, 5, 9, 14, 13, 0, 0, 24, 6, 14, 15, 9, 0, 0, 30, 9, 6, 16], "wmn": 2534, "wmt": 7970, "wmd": 69, "wmv": 23325, "wdn": -32, "wdt": -94, "wdd": -2, "wdv": -11, "tlv": "Connecticut"}