{"loc": "Japan", "iso": "JP", "l1": "Japan", "l2": "Japan", "lvl": 1, "pop": 126476458, "key": 11979, "isd": true, "ppd": 347.778, "med": 48.2, "p65": 27.049, "p70": 18.493, "hos": 13.05, "exp": 84.63, "adr": 1.0, "amn": 13447.0, "amv": 1285436.0, "amd": 139.0, "amt": 185846.0, "tmn": [82, 69, 69, 56, 32, 49, 53, 36, 48, 37, 26, 17, 13, 25, 28, 16, 21, 16, 9, 13, 15], "tmv": [8989, 0, 0, 0, 11684, 14203, 9395, 8756, 0, 0, 0, 0, 14652, 0, 0, 0, 0, 0, 12353, 12019, 0], "tmd": [1, 1, 1, 1, 1, 1, 1, 1, 1, 1, 1, 1, 1, 1, 1, 1, 1, 1, 1, 1, 1], "wmn": 122, "wmt": 2730, "wmd": 3, "wmv": 24373, "wdn": -41, "wdt": -39, "wdd": -23, "wdv": 4, "tlv": "Japan"}