{"loc": "Jefferson", "iso": "US", "l1": "United States", "l2": "Colorado", "lvl": 3, "pop": 582881, "isd": true, "ppd": 35.608, "med": 38.3, "p65": 15.413, "p70": 9.732, "hos": 2.77, "exp": 78.86, "adr": 2.0, "amn": 60534.0, "amv": 118488.0, "amd": 1185.0, "amt": 981731.0, "key": 11998, "tmn": [205, 293, 159, 180, 288, 259, 205, 200, 142, 217, 241, 233, 248, 144, 123, 123, 154, 238, 181, 187, 176], "tmv": [0, 0, 2481, 3099, 4739, 4340, 3978, 2687, 2448, 3374, 4677, 5132, 5139, 4690, 3336, 1695, 3330, 4023, 4903, 6734, 0], "tmd": [2, -1, 19, 2, 7, -1, 2, 0, 6, 0, 2, 6, 0, 0, 0, 2, -3, 4, 13, 0, -1], "wmn": 1186, "wmt": 34987, "wmd": 13, "wmv": 24023, "wdn": -17, "wdt": -2, "wdd": 0, "wdv": -15, "tlv": "Colorado"}