{"loc": "Kamchatka Krai", "iso": "RU", "l1": "Russia", "l2": "Kamchatka Krai", "lvl": 2, "pop": 315557, "key": 12094, "isd": true, "ppd": 8.823, "med": 39.6, "p65": 14.177999999999999, "p70": 9.392999999999999, "hos": 8.05, "exp": 72.58, "adr": 1.0, "amn": 44699.0, "amv": 76631.0, "amd": 618.0, "amt": 822169.0, "tmn": [66, 66, 63, 60, 60, 57, 57, 53, 50, 50, 53, 50, 47, 50, 53, 50, 47, 50, 47, 44, 44], "tmv": [2424, 1547, 1194, 1309, 407, 0, 0, 0, 626, 1894, 826, 384, 15331, 0, 0, 0, 0, 0, 0, 0, 402], "tmd": [13, 20, 10, 16, 13, 16, 10, 10, 13, 16, 13, 10, 16, 7, 0, 0, 0, 0, 0, 0, 0], "wmn": 340, "wmt": 10121, "wmd": 0, "wmv": 403, "wdn": -5, "wdt": 704, "wdd": -100, "wdv": -98, "tlv": "Russia"}