{"loc": "Khabarovsk Krai", "iso": "RU", "l1": "Russia", "l2": "Khabarovsk Krai", "lvl": 2, "pop": 1328302, "key": 12162, "isd": true, "ppd": 8.823, "med": 39.6, "p65": 14.177999999999999, "p70": 9.392999999999999, "hos": 8.05, "exp": 72.58, "adr": 1.0, "amn": 37421.0, "amv": 52756.0, "amd": 235.0, "amt": 791605.0, "tmn": [73, 70, 67, 64, 62, 58, 55, 51, 46, 44, 39, 37, 42, 40, 38, 39, 39, 42, 44, 40, 37], "tmv": [0, 0, 0, 0, 0, 0, 0, 0, 74, 1641, 3572, 1994, 1932, 490, 95, 170, 2424, 1547, 1194, 1309, 407], "tmd": [1, 0, 1, 2, 1, 1, 1, 1, 2, 2, 2, 2, 2, 2, 2, 2, 2, 2, 2, 2, 2], "wmn": 284, "wmt": 0, "wmd": 11, "wmv": 7150, "wdn": -6, "wdt": -100, "wdd": 8, "wdv": -26, "tlv": "Russia"}