{"loc": "Kiev", "iso": "UA", "l1": "Ukraine", "l2": "Kiev", "lvl": 2, "pop": 2950800, "key": 12179, "isd": true, "ppd": 77.39, "med": 41.4, "p65": 16.462, "p70": 11.133, "hos": 8.8, "exp": 72.06, "adr": 2.0, "amn": 48230.0, "amv": 410.0, "amd": 944.0, "amt": 163291.0, "tmn": [104, 124, 173, 184, 140, 67, 57, 153, 185, 220, 253, 196, 70, 52, 156, 221, 294, 308, 231, 146, 96], "tmv": [0, 0, 0, 0, 0, 0, 0, 0, 0, 26, 39, 2, 0, 0, 45, 61, 66, 74, 29, 20, 0], "tmd": [4, 5, 4, 3, 2, 3, 3, 6, 3, 7, 6, 3, 5, 2, 4, 9, 8, 6, 7, 5, 7], "wmn": 1456, "wmt": 5026, "wmd": 42, "wmv": 299, "wdn": 28, "wdt": 67, "wdd": 52, "wdv": 337, "tlv": "Ukraine"}