{"loc": "Kodagu", "iso": "IN", "l1": "India", "l2": "Karnataka", "lvl": 3, "pop": 554762, "key": 12220, "isd": true, "ppd": 450.41900000000004, "med": 28.2, "p65": 5.989, "p70": 3.4139999999999997, "hos": 0.53, "exp": 69.66, "adr": 1.0, "amn": 11053.0, "amv": 8278.0, "amd": 132.0, "amt": 272803.0, "tmn": [10, 10, 18, 16, 12, 1, 3, 19, 10, 0, 10, 3, 0, 7, 5, 0, 3, 5, 5, 5, 5], "tmv": [225, 369, 331, 259, 26, 323, 255, 293, 353, 335, 61, 0, 0, 246, 238, 478, 437, 281, 178, 245, 0], "tmd": [0, 0, 0, 0, 0, 0, 0, 0, 0, 0, 0, 0, 0, 0, 0, 0, 2, 0, 0, 0, 0], "wmn": 31, "wmt": 5714, "wmd": 2, "wmv": 1860, "wdn": -41, "wdt": -8, "wdd": 0, "wdv": 44, "tlv": "Karnataka"}