{"loc": "Krishna", "iso": "IN", "l1": "India", "l2": "Andhra Pradesh", "lvl": 3, "pop": 4529009, "key": 12247, "isd": true, "ppd": 450.41900000000004, "med": 28.2, "p65": 5.989, "p70": 3.4139999999999997, "hos": 0.53, "exp": 69.66, "adr": 1.0, "amn": 10793.0, "amv": 8278.0, "amd": 150.0, "amt": 255554.0, "tmn": [3, 4, 2, 2, 2, 2, 1, 1, 1, 1, 1, 1, 0, 2, 1, 0, 1, 1, 4, 0, 1], "tmv": [225, 369, 331, 259, 26, 323, 255, 293, 353, 335, 61, 0, 0, 246, 238, 478, 437, 281, 178, 245, 0], "tmd": [0, 0, 1, 0, 0, 0, 0, 0, 0, 0, 0, 0, 1, 0, 1, 0, 0, 0, 0, 0, 0], "wmn": 11, "wmt": 3449, "wmd": 1, "wmv": 1860, "wdn": 2, "wdt": -5, "wdd": 0, "wdv": 44, "tlv": "Andhra Pradesh"}