{"loc": "Lambayeque", "iso": "PE", "l1": "Peru", "l2": "Lambayeque", "lvl": 2, "pop": 1310800, "key": 12314, "isd": true, "ppd": 25.129, "med": 29.1, "p65": 7.151, "p70": 4.455, "hos": 1.6, "exp": 76.74, "adr": 14.0, "amn": 43974.0, "amv": 258407.0, "amd": 6256.0, "amt": 133007.0, "tmn": [0, 0, 0, 0, 0, 191, 0, 0, 0, 0, 0, 0, 0, 0, 0, 0, 0, 471, 0, 0, 0], "tmv": [5213, 3405, 993, 3273, 4138, 3734, 2508, 3597, 2263, 1375, 1539, 2597, 4794, 5171, 4965, 4311, 2806, 3902, 4163, 2713, 0], "tmd": [0, 0, 0, 0, 0, 33, 0, 0, 0, 0, 0, 0, 0, 0, 0, 0, 0, 83, 0, 0, 0], "wmn": 472, "wmt": 0, "wmd": 83, "wmv": 22863, "wdn": 0, "wdt": 0, "wdd": 0, "wdv": 7, "tlv": "Peru"}