{"loc": "Latvia", "iso": "LV", "l1": "Latvia", "l2": "0", "lvl": 1, "pop": 1886202, "key": 12340, "isd": true, "ppd": 31.212, "med": 43.9, "p65": 19.754, "p70": 14.136, "hos": 5.57, "exp": 75.29, "adr": 2.0, "amn": 73147.0, "amv": 664320.0, "amd": 1346.0, "amt": 1563422.0, "tmn": [54, 17, 10, 20, 21, 15, 47, 53, 37, 21, 31, 16, 11, 24, 25, 26, 18, 16, 19, 9, 28], "tmv": [167, 41, 1568, 1691, 1189, 8131, 7534, 7718, 6099, 6511, 4529, 1156, 4045, 4595, 5295, 4506, 5776, 4172, 1031, 2964, 2789], "tmd": [0, 2, 1, 2, 0, 0, 3, 3, 4, 4, 0, 2, 0, 2, 2, 1, 1, 0, 0, 0, 2], "wmn": 144, "wmt": 25725, "wmd": 4, "wmv": 26536, "wdn": -27, "wdt": -10, "wdd": -70, "wdv": -23, "tlv": "Latvia"}