{"loc": "Liechtenstein", "iso": "LI", "l1": "Liechtenstein", "l2": "0", "lvl": 1, "pop": 38137, "key": 12413, "isd": true, "ppd": 237.012, "med": -1.0, "p65": -1.0, "p70": -1.0, "hos": 2.397, "exp": 82.49, "adr": 2.0, "amn": 79686.0, "amv": 822115.0, "amd": 1547.0, "amt": 1337232.0, "tmn": [26, 52, 0, 0, 0, 0, 0, 0, 0, 0, 52, 0, 52, 26, 26, 0, 0, 52, 0, 52, 78], "tmv": [15155, 0, 0, 14710, 14605, 14683, 14421, 15208, 0, 0, 0, 13766, 7761, 13582, 7289, 0, 0, 0, 0, 0, 0], "tmd": [27, 0, 0, 0, 0, 0, 0, 0, 0, 0, 0, 0, 0, 0, 0, 0, 0, 0, 0, 0, 0], "wmn": 210, "wmt": 8208, "wmd": 0, "wmv": 7290, "wdn": 60, "wdt": -69, "wdd": 0, "wdv": -86, "tlv": "Liechtenstein"}