{"loc": "Luxembourg", "iso": "LU", "l1": "Luxembourg", "l2": "0", "lvl": 1, "pop": 625976, "key": 12512, "isd": true, "ppd": 231.447, "med": 39.7, "p65": 14.312000000000001, "p70": 9.842, "hos": 4.51, "exp": 82.25, "adr": 1.0, "amn": 120519.0, "amv": 1208155.0, "amd": 1326.0, "amt": 5392787.0, "tmn": [79, 0, 0, 212, 67, 97, 75, 79, 0, 0, 151, 142, 121, 100, 107, 0, 0, 231, 137, 153, 207], "tmv": [5078, 0, 0, 0, 4528, 3813, 3490, 2725, 0, 0, 0, 2461, 2335, 1952, 2027, 0, 0, 0, 1658, 2126, 0], "tmd": [0, 0, 0, 2, 0, 4, 0, 2, 0, 0, 0, 0, 2, 2, 0, 0, 0, 0, 0, 0, 0], "wmn": 838, "wmt": 0, "wmd": 0, "wmv": 5812, "wdn": 40, "wdt": -100, "wdd": -100, "wdv": -39, "tlv": "Luxembourg"}