{"loc": "Lviv Oblast", "iso": "UA", "l1": "Ukraine", "l2": "Lviv Oblast", "lvl": 2, "pop": 2522021, "key": 12515, "isd": true, "ppd": 77.39, "med": 41.4, "p65": 16.462, "p70": 11.133, "hos": 8.8, "exp": 72.06, "adr": 3.0, "amn": 34067.0, "amv": 1087.0, "amd": 942.0, "amt": 166510.0, "tmn": [96, 110, 78, 113, 171, 187, 275, 158, 124, 138, 159, 233, 256, 210, 238, 201, 139, 207, 237, 279, 348], "tmv": [0, 0, 0, 0, 26, 39, 2, 0, 0, 45, 61, 66, 74, 29, 20, 26, 99, 134, 202, 212, 0], "tmd": [2, 0, 4, 3, 5, 2, 6, 3, 0, 6, 2, 4, 4, 2, 4, 0, 0, 5, 5, 5, 6], "wmn": 1652, "wmt": 915, "wmd": 23, "wmv": 698, "wdn": 29, "wdt": -78, "wdd": 19, "wdv": 151, "tlv": "Ukraine"}