{"loc": "Mexico", "iso": "MX", "l1": "Mexico", "l2": "Mexico", "lvl": 2, "pop": 17427790, "isd": true, "ppd": 66.444, "med": 29.3, "p65": 6.857, "p70": 4.321, "hos": 1.38, "exp": 75.05, "adr": 13.0, "amn": 11322.0, "amv": 5480.0, "amd": 1453.0, "amt": 34198.0, "key": 12755, "tmn": [162, 57, 52, 115, 133, 140, 135, 131, 47, 37, 104, 111, 123, 103, 98, 28, 24, 23, 86, 0, 173], "tmv": [358, 69, 159, 43, 22, 401, 488, 30, 84, 121, 56, 29, 14, 34, 63, 23, 14, 18, 70, 66, 40], "tmd": [12, 5, 6, 16, 12, 19, 14, 13, 5, 8, 16, 13, 15, 14, 16, 5, 6, 5, 19, 0, 26], "wmn": 435, "wmt": 520, "wmd": 73, "wmv": 299, "wdn": -34, "wdt": -69, "wdd": -11, "wdv": -20, "tlv": "Mexico"}