{"loc": "Mie", "iso": "JP", "l1": "Japan", "l2": "Mie", "lvl": 2, "pop": 1780882, "key": 12771, "isd": true, "ppd": 347.778, "med": 48.2, "p65": 27.049, "p70": 18.493, "hos": 13.05, "exp": 84.63, "adr": 2.0, "amn": 2909.0, "amv": 228399.0, "amd": 62.0, "amt": 117450.0, "tmn": [10, 12, 12, 12, 14, 14, 12, 7, 5, 8, 5, 10, 8, 6, 10, 2, 2, 3, 2, 7, 2], "tmv": [0, 6854, 6226, 6150, 6575, 0, 0, 0, 8645, 8092, 8000, 8100, 0, 0, 0, 10699, 10578, 10119, 9731, 0, 0], "tmd": [1, 1, 2, 0, 0, 0, 0, 0, 0, 0, 0, 1, 0, 0, 0, 1, 0, 0, 0, 0, 0], "wmn": 31, "wmt": 1681, "wmd": 1, "wmv": 41129, "wdn": -41, "wdt": -53, "wdd": 0, "wdv": 25, "tlv": "Japan"}