{"loc": "Monaco", "iso": "MC", "l1": "Monaco", "l2": "0", "lvl": 1, "pop": 39244, "key": 12816, "isd": true, "ppd": 19347.5, "med": -1.0, "p65": -1.0, "p70": -1.0, "hos": 13.8, "exp": 86.75, "adr": 1.0, "amn": 81235.0, "amv": 0.0, "amd": 841.0, "amt": 0.0, "tmn": [738, 356, 127, 382, 76, 25, 382, 152, 484, 152, 407, 203, 101, 203, 382, 178, 178, 203, 127, 0, 127], "tmv": [0, 0, 0, 0, 0, 0, 0, 0, 0, 0, 0, 0, 0, 0, 0, 0, 0, 0, 0, 0, 0], "tmd": [0, 0, 0, 0, 0, 0, 0, 0, 0, 0, 0, 0, 0, 0, 0, 0, 0, 0, 0, 0, 0], "wmn": 1198, "wmt": 0, "wmd": 0, "wmv": 0, "wdn": -30, "wdt": 0, "wdd": 0, "wdv": 0, "tlv": "Monaco"}