{"loc": "Morelos", "iso": "MX", "l1": "Mexico", "l2": "Morelos", "lvl": 2, "pop": 2044058, "key": 12878, "isd": true, "ppd": 66.444, "med": 29.3, "p65": 6.857, "p70": 4.321000000000001, "hos": 1.38, "exp": 75.05, "adr": 9.0, "amn": 11887.0, "amv": 5681.0, "amd": 1017.0, "amt": 35834.0, "tmn": [139, 64, 254, 192, 245, 186, 218, 159, 23, 22, 140, 0, 641, 507, 492, 37, 340, 20, 63, 112, 64], "tmv": [84, 121, 56, 29, 14, 34, 63, 23, 14, 18, 70, 66, 40, 77, 25, 33, 51, 2, 5, 4, 0], "tmd": [2, 9, 10, 7, 7, 22, 14, 1, 2, 2, 7, 0, 21, 13, 3, 9, 18, 8, 10, 7, 8], "wmn": 1132, "wmt": 503, "wmd": 61, "wmv": 124, "wdn": -24, "wdt": -58, "wdd": 38, "wdv": -60, "tlv": "Mexico"}