{"loc": "Mozambique", "iso": "MZ", "l1": "Mozambique", "l2": "0", "lvl": 1, "pop": 31255435, "isd": true, "ppd": 37.728, "med": 17.7, "p65": 3.158, "p70": 1.87, "hos": 0.7, "exp": 60.85, "adr": 1.0, "amn": 1465.0, "amv": 0.0, "amd": 15.0, "amt": 11615.0, "key": 12906, "tmn": [36, 26, 19, 24, 25, 11, 40, 27, 29, 40, 19, 30, 25, 25, 37, 33, 22, 29, 15, 9, 27], "tmv": [0, 0, 0, 0, 0, 0, 0, 0, 0, 0, 0, 0, 0, 0, 0, 0, 0, 0, 0, 0, 0], "tmd": [1, 1, 1, 1, 1, 2, -1, 1, 1, 1, 1, 1, 1, 1, 1, 1, 1, 1, 1, 1, 1], "wmn": 177, "wmt": 407, "wmd": 3, "wmv": 0, "wdn": -11, "wdt": -41, "wdd": 4, "wdv": 0, "tlv": "Mozambique"}