{"loc": "Neemuch", "iso": "IN", "l1": "India", "l2": "Madhya Pradesh", "lvl": 3, "pop": 825958, "key": 12970, "isd": true, "ppd": 450.41900000000004, "med": 28.2, "p65": 5.989, "p70": 3.4139999999999997, "hos": 0.53, "exp": 69.66, "adr": 1.0, "amn": 4112.0, "amv": 57322.0, "amd": 45.0, "amt": 76116.0, "tmn": [3, 14, 2, 10, 20, 14, 6, 6, 20, 4, 10, 13, 15, 9, 12, 20, 18, 18, 31, 44, 33], "tmv": [2202, 1534, 1506, 1591, 1973, 1840, 334, 2484, 1700, 1669, 1709, 1887, 1565, 188, 422, 1406, 1495, 2660, 3090, 2119, 2264], "tmd": [0, 0, 0, 0, 0, 0, 0, 0, 0, 0, 0, 0, 0, 0, 0, 0, 0, 0, 0, 0, 0], "wmn": 180, "wmt": 2047, "wmd": 0, "wmv": 13460, "wdn": 121, "wdt": -4, "wdd": 0, "wdv": 20, "tlv": "Madhya Pradesh"}