{"loc": "Nigeria", "iso": "NG", "l1": "Nigeria", "l2": "0", "lvl": 1, "pop": 206139587, "key": 13019, "isd": true, "ppd": 209.588, "med": 18.1, "p65": 2.7510000000000003, "p70": 1.4469999999999998, "hos": -1.0, "exp": 54.69, "adr": 1.0, "amn": 805.0, "amv": 9192.0, "amd": 10.0, "amt": 9715.0, "tmn": [0, 0, 0, 0, 0, 0, 0, 0, 0, 0, 0, 0, 0, 0, 0, 0, 0, 0, 0, 0, 0], "tmv": [0, 36, 34, 48, 96, 111, 1581, 181, 60, 153, 77, 169, 74, 19, 131, 83, 54, 93, 186, 67, 0], "tmd": [0, 0, 0, 0, 1, 0, 0, 0, 0, 0, 0, 1, 0, 0, 0, 0, 1, 0, 0, 0, 0], "wmn": 2, "wmt": 0, "wmd": 1, "wmv": 618, "wdn": -12, "wdt": 0, "wdd": 0, "wdv": -16, "tlv": "Nigeria"}