{"loc": "Northampton", "iso": "US", "l1": "United States", "l2": "North Carolina", "lvl": 3, "pop": 19483, "isd": true, "ppd": 35.608, "med": 38.3, "p65": 15.413, "p70": 9.732, "hos": 2.77, "exp": 78.86, "adr": 2.0, "amn": 83406.0, "amv": 131140.0, "amd": 1437.0, "amt": 903343.0, "key": 13049, "tmn": [718, 923, 1077, 769, 205, 410, 667, 718, 821, 0, 1385, 102, 51, 3438, 256, 307, 461, 307, 102, 102, 307], "tmv": [3099, 4739, 4340, 3978, 2687, 2448, 3374, 4677, 5132, 5139, 4690, 3336, 1695, 3330, 4023, 4903, 6734, 6595, 3662, 2393, 0], "tmd": [0, 0, 0, 0, 0, 0, 0, 0, 0, 0, 0, 0, 0, 0, 0, 0, 0, 0, 0, 52, 0], "wmn": 1848, "wmt": 35468, "wmd": 52, "wmv": 28313, "wdn": -72, "wdt": -17, "wdd": 0, "wdv": 1, "tlv": "North Carolina"}