{"loc": "Novosibirsk Oblast", "iso": "RU", "l1": "Russia", "l2": "Novosibirsk Oblast", "lvl": 2, "pop": 2788849, "key": 13065, "isd": true, "ppd": 8.823, "med": 39.6, "p65": 14.177999999999999, "p70": 9.392999999999999, "hos": 8.05, "exp": 72.58, "adr": 4.0, "amn": 15275.0, "amv": 174517.0, "amd": 658.0, "amt": 925107.0, "tmn": [27, 27, 25, 26, 27, 26, 24, 23, 25, 24, 24, 25, 24, 26, 27, 26, 23, 24, 26, 25, 24], "tmv": [685, 934, 272, 396, 3780, 3135, 815, 2057, 0, 0, 399, 5012, 1418, 3488, 3879, 768, 803, 2958, 2354, 2083, 2063], "tmd": [2, 2, 2, 2, 2, 2, 2, 2, 2, 2, 2, 2, 2, 2, 2, 2, 2, 2, 2, 2, 2], "wmn": 178, "wmt": 12804, "wmd": 10, "wmv": 14911, "wdn": 2, "wdt": -5, "wdd": -7, "wdv": 20, "tlv": "Russia"}