{"loc": "Oita", "iso": "JP", "l1": "Japan", "l2": "Oita", "lvl": 2, "pop": 1135434, "key": 13097, "isd": true, "ppd": 347.778, "med": 48.2, "p65": 27.049, "p70": 18.493, "hos": 13.05, "exp": 84.63, "adr": 1.0, "amn": 7043.0, "amv": 1225302.0, "amd": 70.0, "amt": 181690.0, "tmn": [73, 64, 54, 45, 48, 42, 44, 33, 28, 29, 22, 24, 22, 7, 33, 21, 16, 12, 9, 12, 16], "tmv": [0, 0, 0, 0, 26945, 9507, 8989, 0, 0, 0, 11684, 14203, 9395, 8756, 0, 0, 0, 0, 14652, 0, 0], "tmd": [0, 0, 0, 1, 0, 1, 2, 0, 0, 1, 0, 1, 0, 0, 0, 2, 0, 0, 0, 1, 1], "wmn": 123, "wmt": 2314, "wmd": 4, "wmv": 14653, "wdn": -27, "wdt": -58, "wdd": 100, "wdv": -67, "tlv": "Japan"}