{"loc": "Papua New Guinea", "iso": "PG", "l1": "Papua New Guinea", "l2": "0", "lvl": 1, "pop": 8947027, "key": 13223, "isd": true, "ppd": 18.22, "med": 22.6, "p65": 3.8080000000000003, "p70": 2.142, "hos": -1.0, "exp": 64.5, "adr": 1.0, "amn": 1958.0, "amv": 7416.0, "amd": 21.0, "amt": 0.0, "tmn": [0, 0, 0, 0, 0, 0, 0, 21, 0, 0, 0, 5, 0, 0, 0, 0, 0, 0, 0, 14, 5], "tmv": [0, 0, 0, 0, 0, 0, 0, 0, 0, 0, 0, 0, 0, 0, 0, 0, 0, 0, 0, 0, 0], "tmd": [0, 0, 0, 0, 0, 0, 0, 1, 0, 0, 0, 1, 0, 0, 0, 0, 0, 0, 0, 1, 1], "wmn": 20, "wmt": 0, "wmd": 2, "wmv": 0, "wdn": -28, "wdt": 0, "wdd": 100, "wdv": 0, "tlv": "Papua New Guinea"}