{"loc": "Pernambuco", "iso": "BR", "l1": "Brazil", "l2": "Pernambuco", "lvl": 2, "pop": 9557071, "key": 13279, "isd": true, "ppd": 25.04, "med": 33.5, "p65": 8.552, "p70": 5.06, "hos": 2.2, "exp": 75.88, "adr": 4.0, "amn": 30649.0, "amv": 33065.0, "amd": 1139.0, "amt": 0.0, "tmn": [170, 172, 155, 0, 242, 0, 259, 160, 171, 144, 188, 93, 84, 165, 201, 232, 142, 118, 98, 72, 180], "tmv": [1078, 2593, 8, 1535, 716, 243, 1009, 1411, 1347, 1361, 2018, 525, 268, 1486, 1287, 1520, 1545, 1307, 647, 364, 0], "tmd": [2, 4, 3, 0, 5, 0, 6, 4, 3, 3, 3, 2, 2, 4, 4, 4, 3, 4, 2, 2, 3], "wmn": 1047, "wmt": 0, "wmd": 19, "wmv": 6674, "wdn": 4, "wdt": 0, "wdd": 7, "wdv": -21, "tlv": "Brazil"}