{"loc": "Pierce", "iso": "US", "l1": "United States", "l2": "Washington", "lvl": 3, "pop": 904980, "isd": true, "ppd": 35.608, "med": 38.3, "p65": 15.413, "p70": 9.732, "hos": 2.77, "exp": 78.86, "adr": 1.0, "amn": 38799.0, "amv": 118488.0, "amd": 535.0, "amt": 619426.0, "key": 13317, "tmn": [0, 278, 342, 339, 393, 185, 0, 434, 262, 282, 327, 274, 286, 0, 322, 235, 169, 217, 184, 104, 0], "tmv": [0, 0, 2481, 3099, 4739, 4340, 3978, 2687, 2448, 3374, 4677, 5132, 5139, 4690, 3336, 1695, 3330, 4023, 4903, 6734, 0], "tmd": [0, 7, 0, 17, 7, 0, 0, 5, 5, 7, 4, 9, 0, 0, 3, 0, 9, 5, 4, 0, 0], "wmn": 1235, "wmt": 22144, "wmd": 19, "wmv": 24023, "wdn": -34, "wdt": -3, "wdd": -32, "wdv": -15, "tlv": "Washington"}