{"loc": "Piemonte", "iso": "IT", "l1": "Italy", "l2": "Piemonte", "lvl": 2, "pop": 4356406, "key": 13314, "isd": true, "ppd": 205.859, "med": 47.9, "p65": 23.021, "p70": 16.24, "hos": 3.18, "exp": 83.51, "adr": 3.0, "amn": 88750.0, "amv": 1502281.0, "amd": 2715.0, "amt": 1751005.0, "tmn": [24, 23, 56, 64, 61, 63, 56, 36, 24, 59, 52, 61, 60, 64, 44, 20, 44, 72, 65, 88, 89], "tmv": [1707, 3218, 3016, 3066, 3116, 2937, 2179, 1098, 2763, 2777, 2969, 3164, 2964, 2177, 988, 854, 2711, 3118, 3232, 3364, 2376], "tmd": [1, 1, 1, 1, 1, 1, 1, 0, 1, 1, 1, 1, 0, 1, 1, 1, 1, 1, 2, 1, 1], "wmn": 426, "wmt": 32537, "wmd": 4, "wmv": 16647, "wdn": 18, "wdt": -40, "wdd": 75, "wdv": -7, "tlv": "Italy"}