{"loc": "Quebec", "iso": "CA", "l1": "Canada", "l2": "Quebec", "lvl": 2, "pop": 8537674, "key": 13460, "isd": true, "ppd": 4.037, "med": 41.4, "p65": 16.984, "p70": 10.797, "hos": 2.5, "exp": 82.43, "adr": 4.0, "amn": 33225.0, "amv": 41051.0, "amd": 1210.0, "amt": 0.0, "tmn": [123, 128, 128, 141, 126, 99, 96, 115, 131, 115, 122, 106, 85, 78, 93, 105, 93, 90, 78, 94, 86], "tmv": [350, 418, 715, 0, 0, 0, 590, 916, 856, 928, 0, 0, 0, 894, 587, 667, 1264, 0, 0, 0, 0], "tmd": [5, 5, 4, 4, 4, 2, 4, 4, 5, 3, 4, 2, 2, 2, 2, 1, 2, 2, 2, 2, 2], "wmn": 642, "wmt": 0, "wmd": 10, "wmv": 2519, "wdn": -15, "wdt": 0, "wdd": -50, "wdv": -30, "tlv": "Canada"}