{"loc": "Romania", "iso": "RO", "l1": "Romania", "l2": "0", "lvl": 1, "pop": 19237682, "key": 13599, "isd": true, "ppd": 85.12899999999999, "med": 43.0, "p65": 17.85, "p70": 11.69, "hos": 6.892, "exp": 76.05, "adr": 3.0, "amn": 56216.0, "amv": 472621.0, "amd": 1780.0, "amt": 441338.0, "tmn": [3, 3, 2, 1, 3, 2, 1, 1, 3, 1, 1, 2, 3, 1, 2, 1, 1, 2, 2, 4, 3], "tmv": [0, 0, 0, 1882, 1068, 1081, 987, 0, 0, 1460, 0, 0, 0, 0, 0, 0, 0, 0, 0, 0, 0], "tmd": [8, 14, 4, 4, 16, 10, 4, 2, 2, 1, 3, 3, 5, 4, 2, 1, 1, 1, 1, 1, 1], "wmn": 19, "wmt": 2098, "wmd": 5, "wmv": 0, "wdn": 17, "wdt": -50, "wdd": -75, "wdv": -100, "tlv": "Romania"}