{"loc": "Rohtak", "iso": "IN", "l1": "India", "l2": "Haryana", "lvl": 3, "pop": 1058683, "key": 13596, "isd": true, "ppd": 450.41900000000004, "med": 28.2, "p65": 5.989, "p70": 3.4139999999999997, "hos": 0.53, "exp": 69.66, "adr": 1.0, "amn": 11851.0, "amv": 45691.0, "amd": 146.0, "amt": 221002.0, "tmn": [1, 5, 4, 2, 4, 9, 1, 4, 9, 6, 5, 3, 7, 14, 19, 21, 12, 36, 15, 2, 17], "tmv": [954, 347, 1488, 1101, 122, 2202, 1534, 1506, 1591, 1973, 1840, 334, 2484, 1700, 1669, 1709, 1887, 1565, 188, 422, 1406], "tmd": [0, 0, 0, 0, 0, 0, 0, 0, 0, 0, 0, 0, 0, 0, 0, 0, 0, 0, 2, 0, 0], "wmn": 127, "wmt": 5148, "wmd": 2, "wmv": 8851, "wdn": 144, "wdt": -1, "wdd": 0, "wdv": -23, "tlv": "Haryana"}