{"loc": "Roraima", "iso": "BR", "l1": "Brazil", "l2": "Roraima", "lvl": 2, "pop": 605761, "key": 13604, "isd": true, "ppd": 25.04, "med": 33.5, "p65": 8.552, "p70": 5.06, "hos": 2.2, "exp": 75.88, "adr": 2.0, "amn": 180094.0, "amv": 395664.0, "amd": 2806.0, "amt": 0.0, "tmn": [482, 331, 137, 544, 571, 531, 138, 732, 326, 236, 85, 33, 118, 2274, 747, 366, 125, 373, 802, 571, 643], "tmv": [2361, 723, 1856, 3582, 3178, 6635, 1944, 3226, 1232, 0, 0, 0, 5068, 4085, 0, 0, 3633, 6407, 5986, 12050, 0], "tmd": [38, 0, 0, 7, 10, 7, 0, 4, 0, 0, 17, 2, 17, 9, 4, 0, 0, 2, 14, 7, 14], "wmn": 3631, "wmt": 0, "wmd": 38, "wmv": 28078, "wdn": -5, "wdt": 0, "wdd": -18, "wdv": 106, "tlv": "Brazil"}