{"loc": "Sehore", "iso": "IN", "l1": "India", "l2": "Madhya Pradesh", "lvl": 3, "pop": 1311008, "key": 13771, "isd": true, "ppd": 450.41900000000004, "med": 28.2, "p65": 5.989, "p70": 3.4139999999999997, "hos": 0.53, "exp": 69.66, "adr": 2.0, "amn": 2335.0, "amv": 45691.0, "amd": 37.0, "amt": 74581.0, "tmn": [3, 3, 3, 8, 4, 7, 6, 5, 3, 0, 5, 6, 6, 14, 6, 11, 8, 12, 6, 12, 19], "tmv": [954, 347, 1488, 1101, 122, 2202, 1534, 1506, 1591, 1973, 1840, 334, 2484, 1700, 1669, 1709, 1887, 1565, 188, 422, 1406], "tmd": [0, 0, 0, 0, 0, 0, 0, 0, 0, 0, 0, 0, 0, 0, 0, 0, 0, 0, 0, 0, 0], "wmn": 78, "wmt": 2076, "wmd": 0, "wmv": 8851, "wdn": 82, "wdt": 16, "wdd": 0, "wdv": -23, "tlv": "Madhya Pradesh"}