{"loc": "Serbia", "iso": "RS", "l1": "Serbia", "l2": "0", "lvl": 1, "pop": 8737370, "key": 13781, "isd": true, "ppd": 80.291, "med": 41.2, "p65": 17.366, "p70": -1.0, "hos": 5.609, "exp": 76.0, "adr": 1.0, "amn": 51081.0, "amv": 112963.0, "amd": 502.0, "amt": 325741.0, "tmn": [213, 225, 192, 174, 224, 230, 238, 228, 220, 185, 158, 152, 207, 282, 293, 301, 279, 288, 338, 372, 396], "tmv": [1519, 1309, 0, 0, 0, 0, 0, 0, 0, 0, 0, 0, 0, 0, 0, 0, 0, 0, 0, 0, 0], "tmd": [2, 2, 2, 2, 2, 2, 2, 2, 2, 2, 2, 2, 2, 2, 2, 2, 2, 2, 2, 2, 2], "wmn": 2270, "wmt": 5591, "wmd": 13, "wmv": 0, "wdn": 58, "wdt": -28, "wdd": -3, "wdv": 0, "tlv": "Serbia"}