{"loc": "Shizuoka", "iso": "JP", "l1": "Japan", "l2": "Shizuoka", "lvl": 2, "pop": 3643528, "key": 13837, "isd": true, "ppd": 347.778, "med": 48.2, "p65": 27.049, "p70": 18.493, "hos": 13.05, "exp": 84.63, "adr": 2.0, "amn": 1419.0, "amv": 251.0, "amd": 25.0, "amt": 61154.0, "tmn": [2, 4, 2, 4, 6, 2, 4, 8, 6, 9, 6, 4, 3, 8, 7, 2, 4, 7, 4, 2, 4], "tmv": [0, 0, 0, 0, 0, 0, 0, 0, 3, 35, 0, 0, 0, 0, 0, 31, 52, 0, 0, 0, 0], "tmd": [1, 1, 0, 1, 0, 0, 0, 0, 0, 0, 0, 0, 1, 0, 0, 0, 0, 0, 0, 0, 0], "wmn": 34, "wmt": 1746, "wmd": 0, "wmv": 85, "wdn": -29, "wdt": -29, "wdd": -100, "wdv": 117, "tlv": "Japan"}