{"loc": "Shimane", "iso": "JP", "l1": "Japan", "l2": "Shimane", "lvl": 2, "pop": 674346, "key": 13833, "isd": true, "ppd": 347.778, "med": 48.2, "p65": 27.049, "p70": 18.493, "hos": 13.05, "exp": 84.63, "adr": 0.0, "amn": 1129.0, "amv": 690893.0, "amd": 3.0, "amt": 137415.0, "tmn": [1, 0, 4, 2, 0, 23, 0, 37, 25, 29, 0, 14, 10, 19, 11, 10, 13, 20, 0, 25, 28], "tmv": [10613, 10564, 10475, 10178, 10145, 10246, 9238, 7862, 9738, 9476, 4177, 3144, 8511, 7854, 8805, 8810, 8632, 7953, 7039, 6396, 4145], "tmd": [0, 0, 0, 0, 0, 0, 0, 0, 0, 0, 0, 0, 0, 0, 0, 0, 0, 0, 0, 0, 0], "wmn": 110, "wmt": 2869, "wmd": 0, "wmv": 51785, "wdn": -20, "wdt": 6, "wdd": 0, "wdv": 2, "tlv": "Japan"}