{"loc": "Sicilia", "iso": "IT", "l1": "Italy", "l2": "Sicilia", "lvl": 2, "pop": 4999891, "key": 13844, "isd": true, "ppd": 205.859, "med": 47.9, "p65": 23.021, "p70": 16.24, "hos": 3.18, "exp": 83.51, "adr": 2.0, "amn": 60434.0, "amv": 1429825.0, "amd": 1382.0, "amt": 1576717.0, "tmn": [82, 129, 92, 84, 84, 45, 110, 55, 159, 86, 82, 80, 36, 64, 57, 49, 93, 56, 50, 46, 54], "tmv": [4134, 3771, 3858, 3368, 2017, 3640, 3311, 3229, 3272, 2882, 2454, 1328, 2805, 2673, 2556, 2588, 2771, 2392, 1384, 2582, 0], "tmd": [4, 4, 3, 3, 1, 2, 3, 2, 2, 3, 2, 2, 2, 3, 2, 2, 1, 2, 1, 2, 3], "wmn": 408, "wmt": 24573, "wmd": 10, "wmv": 14276, "wdn": -28, "wdt": -25, "wdd": -18, "wdv": -23, "tlv": "Italy"}