{"loc": "Sint Maarten", "iso": "SX", "l1": "Netherlands", "l2": "Sint Maarten", "lvl": 2, "pop": 42882, "isd": true, "ppd": 508.544, "med": 43.2, "p65": 18.779, "p70": 11.881, "hos": 3.32, "exp": 82.28, "adr": 1.0, "amn": 44284.0, "amv": 17724.0, "amd": 630.0, "amt": 346314.0, "key": 13857, "tmn": [513, 279, 0, 349, 303, 186, 606, 116, 373, 0, 676, 116, 209, 932, 349, 582, 139, 0, 396, 349, 326], "tmv": [0, 0, 0, 0, 0, 0, 0, 0, 0, 0, 0, 0, 0, 0, 0, 0, 0, 0, 4188, 1705, 1542], "tmd": [0, 0, 0, 0, 0, 0, 0, 0, 0, 0, 0, 0, 0, 0, 0, 0, 0, 0, 0, 0, 0], "wmn": 2146, "wmt": 0, "wmd": 0, "wmv": 7437, "wdn": -12, "wdt": 0, "wdd": 0, "wdv": 0, "tlv": "Netherlands"}