{"loc": "Solan", "iso": "IN", "l1": "India", "l2": "Himachal Pradesh", "lvl": 3, "pop": 576670, "key": 13891, "isd": true, "ppd": 450.41900000000004, "med": 28.2, "p65": 5.989, "p70": 3.4139999999999997, "hos": 0.53, "exp": 69.66, "adr": 1.0, "amn": 11977.0, "amv": 20448.0, "amd": 127.0, "amt": 154908.0, "tmn": [0, 1, 1, 8, 10, 5, 1, 12, 3, 1, 24, 19, 19, 8, 10, 43, 3, 12, 20, 20, 12], "tmv": [178, 245, 350, 332, 507, 499, 351, 42, 400, 555, 721, 1006, 1081, 1032, 48, 1463, 984, 954, 347, 1488, 0], "tmd": [0, 0, 0, 0, 0, 0, 0, 0, 0, 0, 0, 0, 0, 0, 0, 0, 0, 0, 0, 0, 0], "wmn": 124, "wmt": 3381, "wmd": 0, "wmv": 5288, "wdn": 39, "wdt": -29, "wdd": 0, "wdv": 9, "tlv": "Himachal Pradesh"}