{"loc": "Sonora", "iso": "MX", "l1": "Mexico", "l2": "Sonora", "lvl": 2, "pop": 3074745, "key": 13904, "isd": true, "ppd": 66.444, "med": 29.3, "p65": 6.857, "p70": 4.321000000000001, "hos": 1.38, "exp": 75.05, "adr": 8.0, "amn": 36877.0, "amv": 1004414.0, "amd": 2779.0, "amt": 85501.0, "tmn": [50, 44, 65, 52, 0, 23, 0, 66, 118, 45, 45, 23, 0, 9, 54, 32, 64, 157, 22, 0, 90], "tmv": [3073, 3718, 3806, 4700, 4911, 3432, 12647, 0, 0, 0, 56702, 1905, 703, 0, 0, 2837, 0, 0, 0, 902, 0], "tmd": [2, 2, 4, 5, 0, 2, 0, 4, 12, 4, 1, 8, 0, 3, 5, 2, 4, 7, 1, 0, 5], "wmn": 422, "wmt": 409, "wmd": 21, "wmv": 3740, "wdn": 36, "wdt": -43, "wdd": -29, "wdv": -94, "tlv": "Mexico"}