{"loc": "Sormland", "iso": "SE", "l1": "Sweden", "l2": "Sormland", "lvl": 2, "pop": 297540, "key": 13905, "isd": true, "ppd": 24.718000000000004, "med": 41.0, "p65": 19.985, "p70": 13.433, "hos": 2.22, "exp": 82.8, "adr": 2.0, "amn": 78242.0, "amv": 341732.0, "amd": 1512.0, "amt": 0.0, "tmn": [1176, 715, 537, 0, 0, 0, 1754, 672, 833, 675, 0, 0, 0, 1314, 783, 635, 615, 0, 0, 0, 1451], "tmv": [0, 0, 0, 0, 0, 0, 0, 0, 0, 0, 0, 0, 0, 0, 4398, 7847, 12274, 0, 0, 0, 0], "tmd": [37, 0, 4, 0, 0, 0, 0, 4, 7, 0, 0, 0, 0, 17, 7, 0, 0, 0, 0, 0, 14], "wmn": 3486, "wmt": 0, "wmd": 21, "wmv": 24520, "wdn": 0, "wdt": -100, "wdd": -25, "wdv": 0, "tlv": "Sweden"}