{"loc": "Sormland", "iso": "SE", "l1": "Sweden", "l2": "Sormland", "lvl": 2, "pop": 297540, "key": 13905, "isd": true, "ppd": 24.718000000000004, "med": 41.0, "p65": 19.985, "p70": 13.433, "hos": 2.22, "exp": 82.8, "adr": 2.0, "amn": 81750.0, "amv": 391857.0, "amd": 1519.0, "amt": 0.0, "tmn": [675, 0, 0, 0, 1314, 783, 635, 615, 0, 0, 0, 1451, 598, 547, 534, 0, 0, 0, 1095, 732, 0], "tmv": [0, 0, 0, 0, 0, 0, 0, 0, 0, 0, 0, 0, 0, 7711, 11470, 0, 0, 0, 0, 4713, 0], "tmd": [0, 0, 0, 0, 17, 7, 0, 0, 0, 0, 0, 14, 4, 0, 0, 0, 0, 0, 0, 4, 0], "wmn": 2363, "wmt": 15175, "wmd": 4, "wmv": 16184, "wdn": -26, "wdt": -57, "wdd": -80, "wdv": 110, "tlv": "Sweden"}