{"loc": "Suriname", "iso": "SR", "l1": "Suriname", "l2": "0", "lvl": 1, "pop": 586634, "key": 14037, "isd": true, "ppd": 3.612, "med": 29.6, "p65": 6.933, "p70": 4.229, "hos": 3.1, "exp": 71.68, "adr": 2.0, "amn": 14941.0, "amv": 0.0, "amd": 283.0, "amt": 0.0, "tmn": [110, 93, 97, 93, 105, 117, 85, 121, 66, 59, 18, 81, 100, 66, 40, 52, 35, 32, 34, 49, 44], "tmv": [0, 0, 0, 0, 0, 0, 0, 0, 0, 0, 0, 0, 0, 0, 0, 0, 0, 0, 0, 0, 0], "tmd": [4, 0, 2, 0, 2, 4, 4, 0, 0, 0, 4, 0, 0, 4, 0, 4, 2, 2, 2, 2, 4], "wmn": 290, "wmt": 0, "wmd": 14, "wmv": 0, "wdn": -44, "wdt": 0, "wdd": 100, "wdv": 0, "tlv": "Suriname"}