{"loc": "Taiwan", "iso": "TW", "l1": "Taiwan", "l2": "0", "lvl": 1, "pop": 23816775, "key": 14059, "isd": true, "ppd": -1.0, "med": 42.2, "p65": -1.0, "p70": 8.353, "hos": -1.0, "exp": 80.46, "adr": 5.0, "amn": 689.0, "amv": 1057323.0, "amd": 36.0, "amt": 166880.0, "tmn": [0, 0, 0, 0, 0, 0, 0, 0, 0, 0, 0, 0, 0, 0, 0, 0, 0, 0, 0, 0, 0], "tmv": [10769, 11310, 10886, 17172, 0, 0, 15924, 14127, 15937, 14434, 18988, 0, 0, 21011, 18219, 17614, 17281, 18152, 0, 0, 13094], "tmd": [0, 0, 0, 0, 0, 0, 0, 0, 0, 0, 0, 0, 0, 1, 0, 0, 0, 0, 0, 0, 0], "wmn": 2, "wmt": 3547, "wmd": 0, "wmv": 84363, "wdn": 5, "wdt": -29, "wdd": -100, "wdv": 0, "tlv": "Taiwan"}