{"loc": "Tlaxcala", "iso": "MX", "l1": "Mexico", "l2": "Tlaxcala", "lvl": 2, "pop": 1380011, "key": 14150, "isd": true, "ppd": 66.444, "med": 29.3, "p65": 6.857, "p70": 4.321000000000001, "hos": 1.38, "exp": 75.05, "adr": 10.0, "amn": 21407.0, "amv": 1073379.0, "amd": 2170.0, "amt": 89598.0, "tmn": [0, 7, 14, 3, 0, 5, 6, 0, 14, 0, 13, 0, 12, 2, 0, 5, 10, 0, 0, 2, 13], "tmv": [0, 0, 1733, 0, 0, 1654, 892, 1673, 1597, 3250, 0, 0, 0, 0, 0, 0, 3593, 0, 0, 2663, 0], "tmd": [0, 0, 2, 1, 0, 0, 1, 0, 0, 0, 6, 0, 0, 1, 0, 1, 0, 0, 0, 1, 0], "wmn": 32, "wmt": 160, "wmd": 1, "wmv": 6257, "wdn": -27, "wdt": -77, "wdd": -89, "wdv": -4, "tlv": "Mexico"}