{"loc": "Trinidad and Tobago", "iso": "TT", "l1": "Trinidad and Tobago", "l2": "0", "lvl": 1, "pop": 1399491, "key": 14187, "isd": true, "ppd": 266.88599999999997, "med": 36.2, "p65": 10.014, "p70": 5.819, "hos": 3.0, "exp": 73.51, "adr": 2.0, "amn": 5799.0, "amv": 0.0, "amd": 104.0, "amt": 78832.0, "tmn": [7, 10, 3, 1, 12, 3, 6, 12, 11, 4, 2, 27, 15, 10, 10, 16, 6, 12, 15, 32, 31], "tmv": [0, 0, 0, 0, 0, 0, 0, 0, 0, 0, 0, 0, 0, 0, 0, 0, 0, 0, 0, 0, 0], "tmd": [0, 0, 0, 0, 0, 0, 0, 0, 0, 0, 1, 0, 0, 0, 1, 0, 0, 0, 0, 3, 0], "wmn": 127, "wmt": 1770, "wmd": 3, "wmv": 0, "wdn": 50, "wdt": -19, "wdd": 300, "wdv": 0, "tlv": "Trinidad and Tobago"}