{"loc": "Udmurt Republic", "iso": "RU", "l1": "Russia", "l2": "Udmurt Republic", "lvl": 2, "pop": 1513044, "key": 14225, "isd": true, "ppd": 8.823, "med": 39.6, "p65": 14.177999999999999, "p70": 9.392999999999999, "hos": 8.05, "exp": 72.58, "adr": 3.0, "amn": 21956.0, "amv": 149686.0, "amd": 581.0, "amt": 903997.0, "tmn": [39, 40, 41, 42, 39, 38, 38, 36, 36, 34, 33, 33, 33, 31, 31, 27, 28, 28, 29, 28, 27], "tmv": [1736, 2720, 2175, 3732, 494, 1114, 1656, 3335, 3289, 2127, 685, 934, 272, 396, 3780, 3135, 815, 2057, 0, 0, 399], "tmd": [4, 4, 2, 2, 3, 3, 2, 1, 2, 2, 4, 3, 5, 4, 4, 4, 4, 4, 4, 4, 4], "wmn": 202, "wmt": 10356, "wmd": 25, "wmv": 10189, "wdn": -16, "wdt": 24, "wdd": 37, "wdv": -8, "tlv": "Russia"}