{"loc": "Ukraine", "iso": "UA", "l1": "Ukraine", "l2": "Ukraine", "lvl": 1, "pop": 43733759, "key": 14230, "isd": true, "ppd": 77.39, "med": 41.4, "p65": 16.462, "p70": 11.133, "hos": 8.8, "exp": 72.06, "adr": 2.0, "amn": 39848.0, "amv": 6124.0, "amd": 798.0, "amt": 187039.0, "tmn": [298, 305, 208, 157, 222, 272, 346, 364, 351, 256, 182, 264, 326, 383, 416, 400, 275, 193, 243, 259, 404], "tmv": [212, 82, 46, 204, 0, 0, 0, 0, 90, 62, 249, 769, 0, 0, 0, 0, 0, 330, 426, 392, 436], "tmd": [6, 6, 4, 4, 7, 7, 7, 7, 7, 4, 4, 8, 9, 9, 8, 7, 5, 5, 7, 10, 10], "wmn": 2194, "wmt": 7863, "wmd": 50, "wmv": 1587, "wdn": 3, "wdt": 670, "wdd": 12, "wdv": 35, "tlv": "Ukraine"}