{"loc": "Unknown", "iso": "DE", "l1": "Germany", "l2": "Unknown", "lvl": 2, "pop": 0, "key": 14315, "isd": true, "ppd": 237.016, "med": 46.6, "p65": 21.453000000000003, "p70": 15.957, "hos": 8.0, "exp": 81.33, "adr": 0.0, "amn": 0, "amv": 1112013.0, "amd": 0, "amt": 799837.0, "tmn": [0], "tmv": [9105, 7813, 3229, 2379, 4509, 7158, 8886, 7279, 6685, 2488, 1479, 3950, 6444, 8053, 6725, 5773, 2282, 1370, 3372, 5172, 0], "tmd": [0], "wmn": 0, "wmt": 0, "wmd": 0, "wmv": 24698, "wdn": -237, "wdt": 0, "wdd": 0, "wdv": -32, "tlv": "Germany"}