{"loc": "Unknown", "iso": "MX", "l1": "Mexico", "l2": "Unknown", "lvl": 2, "pop": 0, "key": 14319, "isd": true, "ppd": 66.444, "med": 29.3, "p65": 6.857, "p70": 4.321000000000001, "hos": 1.38, "exp": 75.05, "adr": 0, "amn": 0, "amv": 347326.0, "amd": 0, "amt": 54948.0, "tmn": [0], "tmv": [2088, 4324, 2436, 1776, 2202, 3482, 3011, 4068, 3675, 3194, 1538, 3701, 5220, 6164, 4973, 4520, 3010, 1245, 3698, 0, 0], "tmd": [0], "wmn": 0, "wmt": 283, "wmd": 0, "wmv": 17449, "wdn": 0, "wdt": -64, "wdd": 0, "wdv": -37, "tlv": "Mexico"}