{"loc": "Unknown", "iso": "BE", "l1": "Belgium", "l2": "Unknown", "lvl": 2, "pop": 0, "key": 14312, "isd": true, "ppd": 375.564, "med": 41.8, "p65": 18.570999999999998, "p70": 12.849, "hos": 5.64, "exp": 81.63, "adr": 101.0, "amn": 0, "amv": 1448855.0, "amd": 0, "amt": 1818229.0, "tmn": [0], "tmv": [56, 419, 466, 909, 654, 948, 1135, 28, 447, 620, 916, 608, 904, 884, 14, 280, 357, 610, 364, 0, 0], "tmd": [0], "wmn": 0, "wmt": 19736, "wmd": 0, "wmv": 1629, "wdn": 30, "wdt": -34, "wdd": 38, "wdv": -63, "tlv": "Belgium"}