{"loc": "Zaporizhia Oblast", "iso": "UA", "l1": "Ukraine", "l2": "Zaporizhia Oblast", "lvl": 2, "pop": 1705836, "key": 14699, "isd": true, "ppd": 77.39, "med": 41.4, "p65": 16.462, "p70": 11.133, "hos": 8.8, "exp": 72.06, "adr": 2.0, "amn": 41386.0, "amv": 360.0, "amd": 709.0, "amt": 161486.0, "tmn": [19, 26, 55, 87, 51, 106, 77, 19, 29, 93, 91, 77, 70, 97, 57, 48, 95, 128, 105, 95, 110], "tmv": [0, 0, 0, 0, 0, 0, 0, 0, 0, 0, 0, 26, 39, 2, 0, 0, 45, 61, 66, 74, 0], "tmd": [0, 8, 12, 7, 9, 12, 4, 0, 8, 9, 10, 9, 9, 6, 0, 8, 10, 7, 8, 8, 8], "wmn": 642, "wmt": 3220, "wmd": 46, "wmv": 249, "wdn": 34, "wdt": 7, "wdd": -5, "wdv": 264, "tlv": "Ukraine"}